CHANGES.rst
README.rst
requirements-dev.txt
requirements-test.txt
setup.cfg
setup.py
pyramid_mongokit/__init__.py
pyramid_mongokit.egg-info/PKG-INFO
pyramid_mongokit.egg-info/SOURCES.txt
pyramid_mongokit.egg-info/dependency_links.txt
pyramid_mongokit.egg-info/paster_plugins.txt
pyramid_mongokit.egg-info/requires.txt
pyramid_mongokit.egg-info/top_level.txt