Metadata-Version: 1.0
Name: pyramid-mongokit
Version: 0.2
Summary: Pyramid Mongokit Extension
Home-page: https://github.com/hadrien/pyramid_mongokit
Author: Hadrien David
Author-email: hadrien@ectobal.com
License: UNKNOWN
Platform: UNKNOWN
